Metadata-Version: 2.1
Name: pygac-fdr
Version: 0.2.3
Summary: Python package for creating a Fundamental Data Record (FDR) of AVHRR GAC data using pygac
Home-page: https://github.com/pytroll/pygac-fdr
Author: The Pytroll Team
Author-email: pytroll@googlegroups.com
License: UNKNOWN
Platform: UNKNOWN
Classifier: Development Status :: 4 - Beta
Classifier: Intended Audience :: Science/Research
Classifier: License :: OSI Approved :: GNU General Public License v3 or later (GPLv3+)
Classifier: Operating System :: OS Independent
Classifier: Programming Language :: Python
Classifier: Topic :: Scientific/Engineering
Requires-Python: >=3.10
Provides-Extra: dev
Provides-Extra: tests
License-File: LICENSE
License-File: AUTHORS.md
